LICENSE
README.md
pyproject.toml
setup.py
gemmini/__init__.py
gemmini/canvas.py
gemmini/misc.py
gemmini.egg-info/PKG-INFO
gemmini.egg-info/SOURCES.txt
gemmini.egg-info/dependency_links.txt
gemmini.egg-info/requires.txt
gemmini.egg-info/top_level.txt
gemmini/calc/__init__.py
gemmini/calc/coords.py
gemmini/calc/geometry.py
gemmini/d2/__init__.py
gemmini/d2/_gem2D.py
gemmini/d2/line2D.py
gemmini/d2/point2D.py
gemmini/d2/polar2D.py
gemmini/d2/polygon2D.py
gemmini/d2/shape2D.py
gemmini/d2/transform2D.py
gemmini/test/__init__.py
gemmini/test/test_canvas.py
gemmini/test/test_misc.py
gemmini/test/calc/__init__.py
gemmini/test/calc/test_coords.py
gemmini/test/calc/test_geometry.py
gemmini/test/d2/__init__.py
gemmini/test/d2/test_gem2D.py
gemmini/test/d2/test_line2D.py
gemmini/test/d2/test_point2D.py
gemmini/test/d2/test_polar2D.py
gemmini/test/d2/test_polygon2D.py
gemmini/test/d2/test_shape2D.py
gemmini/test/d2/test_transform2D.py