Metadata-Version: 2.1
Name: gemmini
Version: 1.0.2
Summary: Python package for constructing and handling geometric objects
Home-page: https://github.com/byanko55/gemmini
Author: Yankos
Author-email: byanko55@gmail.com
License: UNKNOWN
Keywords: geometry,drawing 2D/3D graphic
Platform: UNKNOWN
Requires-Python: >=3.7
License-File: LICENSE
